mxcubeweb/__init__.py
mxcubeweb/__version__.py
mxcubeweb/app.py
mxcubeweb/config.py
mxcubeweb/core/__init__.py
mxcubeweb/core/adapter/__init__.py
mxcubeweb/core/adapter/actuator_adapter.py
mxcubeweb/core/adapter/adapter_base.py
mxcubeweb/core/adapter/adapter_manager.py
mxcubeweb/core/adapter/beam_adapter.py
mxcubeweb/core/adapter/beamline_action_adapter.py
mxcubeweb/core/adapter/beamline_adapter.py
mxcubeweb/core/adapter/data_publisher_adapter.py
mxcubeweb/core/adapter/detector_adapter.py
mxcubeweb/core/adapter/diffractometer_adapter.py
mxcubeweb/core/adapter/energy_adapter.py
mxcubeweb/core/adapter/machine_info_adapter.py
mxcubeweb/core/adapter/motor_adapter.py
mxcubeweb/core/adapter/nstate_adapter.py
mxcubeweb/core/adapter/sample_changer_adapter.py
mxcubeweb/core/adapter/sample_view_adapter.py
mxcubeweb/core/adapter/wavelength_adapter.py
mxcubeweb/core/components/__init__.py
mxcubeweb/core/components/chat.py
mxcubeweb/core/components/component_base.py
mxcubeweb/core/components/harvester.py
mxcubeweb/core/components/lims.py
mxcubeweb/core/components/log.py
mxcubeweb/core/components/queue.py
mxcubeweb/core/components/user/__init__.py
mxcubeweb/core/components/user/database.py
mxcubeweb/core/components/user/dummyusermanager.py
mxcubeweb/core/components/user/usermanager.py
mxcubeweb/core/components/workflow.py
mxcubeweb/core/models/__init__.py
mxcubeweb/core/models/adaptermodels.py
mxcubeweb/core/models/configmodels.py
mxcubeweb/core/models/generic.py
mxcubeweb/core/models/usermodels.py
mxcubeweb/core/server/__init__.py
mxcubeweb/core/server/csp.py
mxcubeweb/core/server/db.py
mxcubeweb/core/server/limiter.py
mxcubeweb/core/server/openapidoc.py
mxcubeweb/core/server/resource_handler.py
mxcubeweb/core/server/routes.py
mxcubeweb/core/server/security.py
mxcubeweb/core/server/server.py
mxcubeweb/core/util/__init__.py
mxcubeweb/core/util/convertutils.py
mxcubeweb/core/util/fsutils.py
mxcubeweb/core/util/networkutils.py
mxcubeweb/logging_handler.py
mxcubeweb-4.629.0.dist-info/METADATA
mxcubeweb-4.629.0.dist-info/WHEEL
mxcubeweb-4.629.0.dist-info/entry_points.txt
mxcubeweb-4.629.0.dist-info/licenses/COPYING
mxcubeweb-4.629.0.dist-info/licenses/COPYING.LESSER
mxcubeweb-4.629.0.dist-info/RECORD
