Metadata-Version: 2.4
Name: mxcubeweb
Version: 4.629.0
Summary: MXCuBE Web user interface
License-Expression: LGPL-3.0-or-later
License-File: COPYING
License-File: COPYING.LESSER
Keywords: mxcube,mxcube3,mxcubeweb
Author: The MXCuBE collaboration
Author-email: mxcube@esrf.fr
Maintainer: The MXCuBE collaboration
Maintainer-email: mxcube@esrf.fr
Requires-Python: >=3.10,<3.12
Classifier: Development Status :: 5 - Production/Stable
Classifier: Intended Audience :: Developers
Classifier: Intended Audience :: Science/Research
Classifier: Intended Audience :: End Users/Desktop
Classifier: Natural Language :: English
Classifier: Topic :: Scientific/Engineering
Provides-Extra: graylog
Requires-Dist: Flask (>=3.0.3,<4.0.0)
Requires-Dist: Flask-Security[common,fsqla] (==5.7.1)
Requires-Dist: Flask-SocketIO (>=5.3.6,<6.0.0)
Requires-Dist: authlib (>=1.6.6,<2.0.0)
Requires-Dist: flask-limiter (>=3.12,<4.0)
Requires-Dist: flask-login (>=0.6.3,<0.7.0)
Requires-Dist: gevent (>=23.9.1,<24.0.0)
Requires-Dist: graypy (>=2.1.0) ; extra == "graylog"
Requires-Dist: markupsafe (>=2.1.5,<3.0.0)
Requires-Dist: mxcubecore (>=1.419.0)
Requires-Dist: pillow (>=10.4.0,<11.0.0)
Requires-Dist: pydantic (>=2.8.2,<2.9.0)
Requires-Dist: pytz (>=2022.6,<2023.0)
Requires-Dist: requests (>=2.32.4,<3.0.0)
Requires-Dist: ruamel.yaml (>=0.17.21,<0.18.0)
Requires-Dist: scandir (>=1.10.0,<2.0.0)
Requires-Dist: sqlalchemy (>=2.0.37,<3.0.0)
Requires-Dist: tomli (>=2.2.1,<3.0.0) ; python_full_version <= "3.10.0"
Requires-Dist: tzlocal (>=4.2,<5.0)
Requires-Dist: werkzeug (>=3.1.5,<4.0.0)
Project-URL: Documentation, https://mxcubeweb.readthedocs.io/
Project-URL: Homepage, https://github.com/mxcube/mxcubeweb
Project-URL: Repository, https://github.com/mxcube/mxcubeweb
